Flask_PW-1.1.3.dist-info/DESCRIPTION.rst
Flask_PW-1.1.3.dist-info/METADATA
Flask_PW-1.1.3.dist-info/RECORD
Flask_PW-1.1.3.dist-info/WHEEL
Flask_PW-1.1.3.dist-info/metadata.json
Flask_PW-1.1.3.dist-info/top_level.txt
flask_pw/__init__.py
flask_pw/debugtoolbar.py
flask_pw/models.py
