Metadata-Version: 1.1
Name: Flask-PW
Version: 1.1.3
Summary: Peewee ORM integration for Flask framework
Home-page: https://github.com/klen/flask-pw
Author: Kirill Klenov
Author-email: horneds@gmail.com
License: MIT
Keywords: flask,peewee,migrations,migrate,signals
Platform: Any
Classifier: Development Status :: 4 - Beta
Classifier: Intended Audience :: Developers
Classifier: License :: OSI Approved :: BSD License
Classifier: Natural Language :: English
Classifier: Natural Language :: Russian
Classifier: Operating System :: OS Independent
Classifier: Programming Language :: Python :: 2
Classifier: Programming Language :: Python :: 3
Classifier: Programming Language :: Python
Classifier: Topic :: Software Development :: Libraries :: Python Modules
Classifier: Topic :: Software Development :: Testing
Classifier: Topic :: Utilities
